inspqcommun/__init__.py
inspqcommun/fa/__init__.py
inspqcommun/fa/chargement_service.py
inspqcommun/fa/chargeur_fichiers.py
inspqcommun/fa/configuration.py
inspqcommun/fa/injecteur.py
inspqcommun/fa/convertisseurs/__init__.py
inspqcommun/fa/convertisseurs/convertisseur_acte_vaccinal.py
inspqcommun/fa/convertisseurs/convertisseur_base.py
inspqcommun/fa/convertisseurs/convertisseur_usager.py
inspqcommun/fa/ressources/__init__.py
inspqcommun/fa/ressources/acte_vaccinal.py
inspqcommun/fa/ressources/lieu_vaccination.py
inspqcommun/fa/ressources/organisation.py
inspqcommun/fa/ressources/ressource.py
inspqcommun/fa/ressources/usager.py
inspqcommun/fa/ressources/vaccinateur.py
inspqcommun/fa/validateurs/__init__.py
inspqcommun/fa/validateurs/validateur.py
inspqcommun/fa/validateurs/validateur_acte_vaccinal.py
inspqcommun/fa/validateurs/validateur_usager.py
inspqcommun/fhir/__init__.py
inspqcommun/fhir/clients/__init__.py
inspqcommun/fhir/clients/base_client.py
inspqcommun/fhir/clients/condition_client.py
inspqcommun/fhir/clients/flag_client.py
inspqcommun/fhir/clients/immunization_client.py
inspqcommun/fhir/clients/location_client.py
inspqcommun/fhir/clients/medication_client.py
inspqcommun/fhir/clients/organization_client.py
inspqcommun/fhir/clients/patient_client.py
inspqcommun/fhir/clients/practitioner_client.py
inspqcommun/fhir/clients/value_set_client.py
inspqcommun/fhir/visitors/__init__.py
inspqcommun/fhir/visitors/base.py
inspqcommun/fhir/visitors/bundle.py
inspqcommun/fhir/visitors/condition.py
inspqcommun/fhir/visitors/flag.py
inspqcommun/fhir/visitors/immunization.py
inspqcommun/fhir/visitors/immunization_recommendation.py
inspqcommun/fhir/visitors/location.py
inspqcommun/fhir/visitors/medication.py
inspqcommun/fhir/visitors/operation_outcome.py
inspqcommun/fhir/visitors/organization.py
inspqcommun/fhir/visitors/parameters.py
inspqcommun/fhir/visitors/patient.py
inspqcommun/fhir/visitors/practitioner.py
inspqcommun/fhir/visitors/value_set.py
inspqcommun-2.21.1.dist-info/licenses/LICENSE
inspqcommun-2.21.1.dist-info/METADATA
inspqcommun-2.21.1.dist-info/WHEEL
inspqcommun-2.21.1.dist-info/top_level.txt
inspqcommun-2.21.1.dist-info/RECORD
