Metadata-Version: 2.4
Name: inspqcommun
Version: 2.21.1
Summary: Librairies communes de INSPQ
Home-page: https://gitlab.forge.gouv.qc.ca/inspq/commun/python/inspqcommun.git
Author: Philippe Gauthier
Author-email: philippe.gauthier@inspq.qc.ca
License: LiLiQ
License-File: LICENSE
Requires-Dist: fhirclient==1.0.3
Requires-Dist: wheel
Requires-Dist: urllib3
Requires-Dist: requests
Requires-Dist: pyjwt
Requires-Dist: jinja2
Requires-Dist: PyYAML
Requires-Dist: confluent_kafka
Requires-Dist: pygelf
Requires-Dist: six
Requires-Dist: str2bool
Requires-Dist: python-dateutil
Dynamic: author
Dynamic: author-email
Dynamic: description
Dynamic: home-page
Dynamic: license
Dynamic: license-file
Dynamic: requires-dist
Dynamic: summary
